extractify/__init__.py
extractify/converters.py
extractify/main.py
extractify-0.0.4.dist-info/METADATA
extractify-0.0.4.dist-info/WHEEL
extractify-0.0.4.dist-info/entry_points.txt
extractify-0.0.4.dist-info/top_level.txt
extractify-0.0.4.dist-info/RECORD
