Metadata-Version: 2.1
Name: extractify
Version: 0.0.4
Requires-Dist: tika
Requires-Dist: openpyxl
Requires-Dist: argparse
Requires-Dist: tqdm
Requires-Dist: boto3
